version.py
ansible_roles_ctl-2.0.0.data/scripts/ansible-roles-ctl
ansible_roles_ctl-2.0.0.dist-info/COPYING
ansible_roles_ctl-2.0.0.dist-info/METADATA
ansible_roles_ctl-2.0.0.dist-info/WHEEL
ansible_roles_ctl-2.0.0.dist-info/top_level.txt
ansible_roles_ctl-2.0.0.dist-info/RECORD
