Metadata-Version: 2.1
Name: ansible-roles-ctl
Version: 2.0.0
Summary: Ansible roles management
Home-page: https://gitlab.com/osci/ansible-roles-ctl
Author: Marc Dequènes (Duck)
Author-email: duck@redhat.com
License: GPLv3
Keywords: ansible
Platform: UNKNOWN
Classifier: Environment :: Console
Classifier: Development Status :: 5 - Production/Stable
Classifier: Intended Audience :: System Administrators
Classifier: License :: OSI Approved :: GNU General Public License v3 or later (GPLv3+)
Classifier: Operating System :: OS Independent
Classifier: Programming Language :: Python :: 3 :: Only
Classifier: Topic :: System :: Systems Administration
Classifier: Natural Language :: English
Requires-Python: >=3.4
License-File: COPYING
Requires-Dist: gitpython (>=3.1)
Requires-Dist: argcomplete (>=1.9.2)
Requires-Dist: pyyaml
